sslpsk_pmd3/_sslpsk_openssl3.cpython-312-darwin.so
sslpsk_pmd3/_sslpsk_openssl1.cpython-312-darwin.so
sslpsk_pmd3/sslpsk.py
sslpsk_pmd3/_version.py
sslpsk_pmd3/_sslpsk.c
sslpsk_pmd3/__init__.py
sslpsk_pmd3/test/__init__.py
sslpsk_pmd3/test/example_client.py
sslpsk_pmd3/test/test_sslpsk.py
sslpsk_pmd3/test/example_server.py
sslpsk_pmd3/test/__main__.py
sslpsk_pmd3-1.0.3.dist-info/RECORD
sslpsk_pmd3-1.0.3.dist-info/LICENSE
sslpsk_pmd3-1.0.3.dist-info/WHEEL
sslpsk_pmd3-1.0.3.dist-info/NOTICE
sslpsk_pmd3-1.0.3.dist-info/top_level.txt
sslpsk_pmd3-1.0.3.dist-info/METADATA
