Metadata-Version: 2.1
Name: sslpsk-pmd3
Version: 1.0.3
Summary: sslpsk fork for pymobiledevice3
Author-email: doronz88 <doron88@gmail.com>
Maintainer-email: doronz88 <doron88@gmail.com>
License: 
Project-URL: Homepage, https://github.com/doronz88/sslpsk-pmd3
Project-URL: Bug Reports, https://github.com/doronz88/sslpsk-pmd3/issues
Keywords: ssl,tls,psk,tls-psk,preshared key
Classifier: Development Status :: 5 - Production/Stable
Classifier: Programming Language :: Python :: 3
Classifier: Programming Language :: Python :: 3.8
Classifier: Programming Language :: Python :: 3.9
Classifier: Programming Language :: Python :: 3.10
Classifier: Programming Language :: Python :: 3.11
Classifier: Programming Language :: Python :: 3.12
Classifier: Programming Language :: Python :: 3 :: Only
Requires-Python: >=3.8
License-File: LICENSE
License-File: NOTICE
Provides-Extra: test
Requires-Dist: pytest; extra == "test"
